pandamap/__init__.py
pandamap/cli.py
pandamap/core.py
pandamap/improved_interaction_detection.py
pandamap-3.7.dist-info/licenses/LICENSE
pandamap-3.7.dist-info/METADATA
pandamap-3.7.dist-info/WHEEL
pandamap-3.7.dist-info/entry_points.txt
pandamap-3.7.dist-info/top_level.txt
pandamap-3.7.dist-info/RECORD
