Metadata-Version: 2.4
Name: pandamap
Version: 3.7
Summary: A Python package for visualizing protein-ligand interactions with 2D ligand structure representation
Author-email: "Dr. Pritam Kumar Panda" <pritam@stanford.edu>
License-Expression: MIT
Project-URL: Homepage, https://github.com/yourusername/pandamap
Project-URL: Bug Tracker, https://github.com/yourusername/pandamap/issues
Keywords: bioinformatics,protein-ligand,interactions,visualization,drug-design
Classifier: Programming Language :: Python :: 3
Classifier: Operating System :: OS Independent
Classifier: Topic :: Scientific/Engineering :: Bio-Informatics
Classifier: Topic :: Scientific/Engineering :: Chemistry
Classifier: Topic :: Scientific/Engineering :: Visualization
Requires-Python: >=3.7
License-File: LICENSE
Requires-Dist: numpy>=1.20.0
Requires-Dist: matplotlib>=3.4.0
Requires-Dist: biopython>=1.79
Requires-Dist: requests>=2.25.0
Dynamic: license-file
